LICENSE
README.md
setup.py
geektest.egg-info/PKG-INFO
geektest.egg-info/SOURCES.txt
geektest.egg-info/dependency_links.txt
geektest.egg-info/requires.txt
geektest.egg-info/top_level.txt
modes/__init__.py