Metadata-Version: 2.1
Name: geektest
Version: 1.0.5
Summary: simple tutorial package
Author: geek
License-File: LICENSE
